[
  {
    "question_id":"M1-ALG-001",
    "question_text":"Solve for $x$: $3x - 7 = 8$",
    "answer":"5",
    "difficulty":"Beginner",
    "topic":"Algebra",
    "sub_topic":"Solving Linear Equations",
    "concept":"Linear Equations",
    "hint1":"Try isolating the term with 'x' on one side of the equation.",
    "hint2":"What operation is the opposite of subtraction?",
    "detailed_solution":"1. Add 7 to both sides: 3x - 7 + 7 = 8 + 7  =>  3x = 15. 2. Divide both sides by 3: 3x \/ 3 = 15 \/ 3  =>  x = 5.",
    "grade_level":"7"
  },
  {
    "question_id":"M1-ALG-002",
    "question_text":"Expand and simplify: $2(a + 4) + 3(a - 1)$",
    "answer":"5a + 5",
    "difficulty":"Intermediate",
    "topic":"Algebra",
    "sub_topic":"Expansion and Simplification",
    "concept":"Algebraic Expansion",
    "hint1":"Think about what the question is asking.",
    "hint2":"Break it into smaller steps.",
    "detailed_solution":"Step-by-step solution for M1-ALG-002.",
    "grade_level":"8"
  },
  {
    "question_id":"M1-GEO-001",
    "question_text":"Find the gradient of the line passing through the points (2, 5) and (4, 9).",
    "answer":"2",
    "difficulty":"Intermediate",
    "topic":"Coordinate Geometry",
    "sub_topic":"Linear Equations",
    "concept":"Gradient of a Line",
    "hint1":"Think about what the question is asking.",
    "hint2":"Break it into smaller steps.",
    "detailed_solution":"Step-by-step solution for M1-GEO-001.",
    "grade_level":"9"
  },
  {
    "question_id":"M1-TRI-001",
    "question_text":"What is the value of sin(60\u00b0)?",
    "answer":"$\\frac{\\sqrt{3}}{2}$",
    "difficulty":"Beginner",
    "topic":"Trigonometry",
    "sub_topic":"Sine, Cosine, Tangent",
    "concept":"Basic Trigonometric Ratios",
    "hint1":"Think about what the question is asking.",
    "hint2":"Break it into smaller steps.",
    "detailed_solution":"Step-by-step solution for M1-TRI-001.",
    "grade_level":"10"
  },
  {
    "question_id":"M1-GEO-002",
    "question_text":"A triangle has sides of length 6 cm, 8 cm, and 10 cm.  Is it a right-angled triangle?  Explain.",
    "answer":"Yes, because $6^2 + 8^2 = 10^2$ (36 + 64 = 100).",
    "difficulty":"Intermediate",
    "topic":"Geometry",
    "sub_topic":"Pythagorean Theorem",
    "concept":"Pythagorean Theorem",
    "hint1":"Think about what the question is asking.",
    "hint2":"Break it into smaller steps.",
    "detailed_solution":"Step-by-step solution for M1-GEO-002.",
    "grade_level":"9"
  },
  {
    "question_id":"M1-ALG-003",
    "question_text":"Simplify: $\\frac{12x^3y^2}{4xy}$",
    "answer":"$3x^2y$",
    "difficulty":"Intermediate",
    "topic":"Algebra",
    "sub_topic":"Simplification of Algebraic Expressions",
    "concept":"Laws of Exponents",
    "hint1":"Think about what the question is asking.",
    "hint2":"Break it into smaller steps.",
    "detailed_solution":"Step-by-step solution for M1-ALG-003.",
    "grade_level":"8"
  },
  {
    "question_id":"M1-MEN-001",
    "question_text":"Calculate the area of a circle with a radius of 10 cm. (Use \u03c0 \u2248 3.14)",
    "answer":"314",
    "difficulty":"Intermediate",
    "topic":"Mensuration",
    "sub_topic":"Circles",
    "concept":"Area of a Circle",
    "hint1":"Think about what the question is asking.",
    "hint2":"Break it into smaller steps.",
    "detailed_solution":"Step-by-step solution for M1-MEN-001.",
    "grade_level":"8"
  },
  {
    "question_id":"M1-STA-001",
    "question_text":"Find the median of the following data set: 4, 7, 2, 9, 5, 1, 6.",
    "answer":"5",
    "difficulty":"Beginner",
    "topic":"Statistics",
    "sub_topic":"Measures of Central Tendency",
    "concept":"Median",
    "hint1":"Think about what the question is asking.",
    "hint2":"Break it into smaller steps.",
    "detailed_solution":"Step-by-step solution for M1-STA-001.",
    "grade_level":"7"
  },
  {
    "question_id":"M1-ALG-004",
    "question_text":"Solve the inequality: 2x + 3 < 9",
    "answer":"x < 3",
    "difficulty":"Intermediate",
    "topic":"Algebra",
    "sub_topic":"Solving Linear Inequalities",
    "concept":"Linear Inequalities",
    "hint1":"Think about what the question is asking.",
    "hint2":"Break it into smaller steps.",
    "detailed_solution":"Step-by-step solution for M1-ALG-004.",
    "grade_level":"9"
  },
  {
    "question_id":"M1-PRO-001",
    "question_text":"A bag contains 3 red balls and 5 blue balls. What is the probability of selecting a red ball at random?",
    "answer":"$\\frac{3}{8}$",
    "difficulty":"Beginner",
    "topic":"Probability",
    "sub_topic":"Simple Probability",
    "concept":"Basic Probability",
    "hint1":"Think about what the question is asking.",
    "hint2":"Break it into smaller steps.",
    "detailed_solution":"Step-by-step solution for M1-PRO-001.",
    "grade_level":"9"
  },
  {
    "question_id":"M1-ALG-005",
    "question_text":"Factorize: $x^2 - 5x + 6$",
    "answer":"(x - 2)(x - 3)",
    "difficulty":"Intermediate",
    "topic":"Algebra",
    "sub_topic":"Quadratic Equations",
    "concept":"Factorization",
    "hint1":"Think about what the question is asking.",
    "hint2":"Break it into smaller steps.",
    "detailed_solution":"Step-by-step solution for M1-ALG-005.",
    "grade_level":"9"
  },
  {
    "question_id":"M1-STA-002",
    "question_text":"Find the mode of the data set: 2, 3, 4, 4, 5, 6, 4, 7",
    "answer":"4",
    "difficulty":"Beginner",
    "topic":"Statistics",
    "sub_topic":"Measures of Central Tendency",
    "concept":"Mode",
    "hint1":"Think about what the question is asking.",
    "hint2":"Break it into smaller steps.",
    "detailed_solution":"Step-by-step solution for M1-STA-002.",
    "grade_level":"7"
  },
  {
    "question_id":"M1-MEN-002",
    "question_text":"Convert 3.5 km to meters.",
    "answer":"3500",
    "difficulty":"Beginner",
    "topic":"Mensuration",
    "sub_topic":"Length",
    "concept":"Metric Conversion",
    "hint1":"Think about what the question is asking.",
    "hint2":"Break it into smaller steps.",
    "detailed_solution":"Step-by-step solution for M1-MEN-002.",
    "grade_level":"6"
  }
]